{
  "bio": "not a ZENIN anymore ...",
  "theme": "terminal",
  "featured": [
    "kronos",
    "GSA-Dashboard",
    "BagEnd"
  ],
  "hidden": [
    "svTSXte",
    "payloadPY",
    "cert"
  ],
  "overrides": {
    "kronos": {
      "title": "kronos",
      "description": "",
      "demo": "https://arcofchanu.github.io/kronos/",
      "image": "https://i.postimg.cc/jjjNj8Cv/Copy-of-Hey-just-a-little-reminder-not-everything-has-to-work-out-right-now-(2).png",
      "images": [
        "https://i.postimg.cc/rmqpmHWH/Screenshot-2026-06-30-234523.png",
        "https://i.postimg.cc/MTzGTLR4/Screenshot-2026-06-30-234510.png",
        "https://i.postimg.cc/76qL6R7Q/Screenshot-2026-06-30-234536.png"
      ]
    },
    "GSA-Dashboard": {
      "title": "GSA-Dashboard",
      "description": "",
      "demo": "https://arcofchanu.github.io/GSA-Dashboard/",
      "image": "https://i.postimg.cc/GpZ0p5qw/Chat-GPT-Image-Jun-27-2026-02-23-27-AM.png"
    },
    "BagEnd": {
      "title": "BagEnd",
      "description": "",
      "demo": "https://arcofchanu.github.io/BagEnd/",
      "image": "https://i.postimg.cc/xdFbJCdS/Chat-GPT-Image-Jul-17-2026-09-19-11-PM.jpg"
    },
    "devstore": {
      "title": "devstore",
      "description": "My DevStore configuration",
      "demo": "",
      "image": ""
    },
    "arkenSTONE": {
      "title": "arkenSTONE",
      "description": "",
      "demo": "https://arcofchanu.github.io/arkenSTONE/",
      "image": ""
    },
    "Frame01": {
      "title": "Frame01",
      "description": "",
      "demo": "https://frame01.studio",
      "image": "",
      "images": []
    },
    "G0DM0D3": {
      "title": "G0DM0D3",
      "description": "LIBERATED AI CHAT",
      "demo": "",
      "image": ""
    },
    "OBLITERATUS": {
      "title": "OBLITERATUS",
      "description": "OBLITERATE THE CHAINS THAT BIND YOU",
      "demo": "https://huggingface.co/spaces/pliny-the-prompter/",
      "image": ""
    },
    "svTSXte": {
      "title": "svTSXte",
      "description": "convert .tsx - .svelte and viceversa locally without ( I N T E R N E T)",
      "demo": "",
      "image": ""
    },
    "cert": {
      "title": "cert",
      "description": "only for fun !!",
      "demo": "https://cert-beta.vercel.app",
      "image": ""
    }
  },
  "about": {
    "nameplate": "GAMER • Red Teamer",
    "bio": "not a ZENIN anymore ...",
    "displayName": "",
    "avatarUrl": ""
  },
  "folders": {
    "extension": [
      "GSA-Extractor",
      "De-Fi-paper-trading"
    ]
  }
}